mind_metrics/__init__.py
mind_metrics/__main__.py
mind_metrics/cli.py
mind_metrics/analysis/__init__.py
mind_metrics/analysis/burnout.py
mind_metrics/analysis/correlations.py
mind_metrics/analysis/statistics.py
mind_metrics/data/__init__.py
mind_metrics/data/cleaner.py
mind_metrics/data/loader.py
mind_metrics/utils/__init__.py
mind_metrics/utils/logger.py
mind_metrics/utils/validation.py
mind_metrics/visualization/__init__.py
mind_metrics/visualization/dashboard.py
mind_metrics/visualization/plots.py
mind_metrics-1.0.1.dist-info/METADATA
mind_metrics-1.0.1.dist-info/WHEEL
mind_metrics-1.0.1.dist-info/entry_points.txt
mind_metrics-1.0.1.dist-info/licenses/LICENSE.md
mind_metrics-1.0.1.dist-info/RECORD
