Metadata-Version: 2.4
Name: mind-metrics
Version: 1.0.1
Summary: Workplace Mental Health Analytics - A comprehensive data analysis application for mental health survey data
Project-URL: Documentation, https://your-team.gitlab.io/mind-metrics/
Project-URL: Repository, https://gitlab.com/your-team/mind-metrics
Project-URL: Bug Tracker, https://gitlab.com/your-team/mind-metrics/-/issues
Project-URL: Changelog, https://gitlab.com/your-team/mind-metrics/-/blob/main/CHANGELOG.md
Project-URL: PyPI, https://test.pypi.org/project/mind-metrics/
Author-email: Mind Metrics Team <team@mindmetrics.dev>
Maintainer-email: Lead Developer <lead@mindmetrics.dev>
License: # MIT License
License-File: LICENSE.md
Keywords: burnout-analysis,data-visualization,employee-wellbeing,mental-health,statistics,workplace-analytics
Classifier: Development Status :: 4 - Beta
Classifier: Intended Audience :: Healthcare Industry
Classifier: Intended Audience :: Science/Research
Classifier: License :: OSI Approved :: MIT License
Classifier: Operating System :: OS Independent
Classifier: Programming Language :: Python :: 3
Classifier: Programming Language :: Python :: 3.9
Classifier: Programming Language :: Python :: 3.10
Classifier: Programming Language :: Python :: 3.11
Classifier: Programming Language :: Python :: 3.12
Classifier: Topic :: Scientific/Engineering :: Information Analysis
Classifier: Topic :: Scientific/Engineering :: Visualization
Classifier: Typing :: Typed
Requires-Python: >=3.9
Requires-Dist: click>=8.1.0
Requires-Dist: matplotlib>=3.7.0
Requires-Dist: numpy>=1.24.0
Requires-Dist: openpyxl>=3.1.0
Requires-Dist: pandas>=2.0.0
Requires-Dist: plotly>=5.17.0
Requires-Dist: pydantic>=2.5.0
Requires-Dist: requests>=2.31.0
Requires-Dist: rich>=13.7.0
Requires-Dist: scikit-learn>=1.3.0
Requires-Dist: scipy>=1.10.0
Requires-Dist: seaborn>=0.12.0
Requires-Dist: typer>=0.9.0
